{
    "kanji": "旧",
    "grade": 5,
    "jlpt": 2,
    "meanings": [
        "old times",
        "old things",
        "old friend",
        "former",
        "ex-"
    ],
    "kun": [
        "ふる.い",
        "もと"
    ],
    "on": [
        "キュウ"
    ],
    "strokes": [
        [
            "M",
            0.21247706422018348,
            0.21100917431192662,
            "c",
            0.00963302752293578,
            0.00963302752293578,
            0.015596330275229357,
            0.022935779816513763,
            0.015596330275229357,
            0.03504587155963303,
            "c",
            0,
            0.007064220183486239,
            -0.0014678899082568807,
            0.3900917431192661,
            -0.001834862385321101,
            0.5475229357798165,
            "c",
            -0.00009174311926605505,
            0.02642201834862385,
            -0.00009174311926605505,
            0.04651376146788991,
            -0.00009174311926605505,
            0.05733944954128441
        ],
        [
            "M",
            0.42201834862385323,
            0.21376146788990827,
            "c",
            0.010091743119266056,
            0.010091743119266056,
            0.013853211009174311,
            0.023211009174311924,
            0.013853211009174311,
            0.041834862385321095,
            "c",
            0,
            0.030091743119266053,
            0,
            0.381559633027523,
            0,
            0.529908256880734,
            "c",
            0,
            0.03293577981651376,
            0,
            0.05587155963302752,
            0,
            0.06311926605504586
        ],
        [
            "M",
            0.44541284403669723,
            0.23211009174311928,
            "c",
            0.03247706422018349,
            -0.0022935779816513763,
            0.2753211009174312,
            -0.027522935779816515,
            0.304954128440367,
            -0.030275229357798163,
            "c",
            0.024678899082568807,
            -0.0022935779816513763,
            0.04091743119266055,
            0.011467889908256881,
            0.04091743119266055,
            0.03724770642201834,
            "c",
            0,
            0.022752293577981652,
            -0.00045871559633027525,
            0.37935779816513765,
            -0.0006422018348623854,
            0.5257798165137615,
            "c",
            0,
            0.03513761467889908,
            -0.00009174311926605505,
            0.05798165137614679,
            -0.00009174311926605505,
            0.06064220183486239
        ],
        [
            "M",
            0.44431192660550456,
            0.5044954128440368,
            "c",
            0.0763302752293578,
            -0.006788990825688073,
            0.2877064220183486,
            -0.027889908256880733,
            0.3375229357798165,
            -0.027889908256880733
        ],
        [
            "M",
            0.4477064220183486,
            0.7955045871559633,
            "C",
            0.5493577981651376,
            0.7889908256880734,
            0.6708256880733945,
            0.7798165137614679,
            0.7802752293577981,
            0.7768807339449542
        ]
    ],
    "words": [
        {
            "word": [
                [
                    "旧",
                    "きゅう"
                ]
            ],
            "common": true,
            "jlpt": 3,
            "meanings": [
                {
                    "type": "Prefix",
                    "meaning": "1. old; former; ex- "
                },
                {
                    "type": "Noun",
                    "meaning": "2. the old; old things; old customs "
                },
                {
                    "type": "Noun",
                    "meaning": "3. old times; bygone days "
                },
                {
                    "type": "Noun, Prefix",
                    "meaning": "4. Japan's old (lunisolar) calendar Abbreviation, See also 旧暦"
                },
                {
                    "type": "Prefix",
                    "meaning": "1. old; former; ex- "
                },
                {
                    "type": "Noun",
                    "meaning": "2. the old; old things; old customs "
                },
                {
                    "type": "Noun",
                    "meaning": "3. old times; bygone days "
                },
                {
                    "type": "Noun, Prefix",
                    "meaning": "4. Japan's old (lunisolar) calendar Abbreviation, See also 旧暦"
                }
            ],
            "sentences": []
        },
        {
            "word": [
                [
                    "元",
                    "もと"
                ]
            ],
            "common": false,
            "jlpt": 3,
            "meanings": [
                {
                    "type": "Noun which may take the genitive case particle 'no', Noun, used as a prefix",
                    "meaning": "1. former; ex-; past; one-time うちのかみさんは元プロレスラーで、だからもし私が浮気をしているところを見つかりでもしようものなら、それこそコテンパンにやられてしまうよ。My wife used to be a pro-wrestler, so if she ever catches me two-timing her, I'd be beaten to a pulp."
                },
                {
                    "type": "Noun, Noun which may take the genitive case particle 'no'",
                    "meaning": "2. earlier times; the past; previous state "
                },
                {
                    "type": "Noun, Adverb (fukushi)",
                    "meaning": "3. formerly; previously; originally; before "
                },
                {
                    "type": "Other forms",
                    "meaning": "旧 【もと】、故 【もと】"
                },
                {
                    "type": "Noun which may take the genitive case particle 'no', Noun, used as a prefix",
                    "meaning": "1. former; ex-; past; one-time うちのかみさんは元プロレスラーで、だからもし私が浮気をしているところを見つかりでもしようものなら、それこそコテンパンにやられてしまうよ。My wife used to be a pro-wrestler, so if she ever catches me two-timing her, I'd be beaten to a pulp."
                },
                {
                    "type": "Noun, Noun which may take the genitive case particle 'no'",
                    "meaning": "2. earlier times; the past; previous state "
                },
                {
                    "type": "Noun, Adverb (fukushi)",
                    "meaning": "3. formerly; previously; originally; before "
                },
                {
                    "type": "Other forms",
                    "meaning": "旧 【もと】、故 【もと】"
                }
            ],
            "sentences": [
                {
                    "sentence": [
                        [
                            "うちの",
                            null
                        ],
                        [
                            "かみさん",
                            null
                        ],
                        [
                            "は",
                            null
                        ],
                        [
                            "元",
                            null
                        ],
                        [
                            "プロレスラー",
                            null
                        ],
                        [
                            "で",
                            null
                        ],
                        [
                            "だから",
                            null
                        ],
                        [
                            "もし",
                            null
                        ],
                        [
                            "私",
                            "わたし"
                        ],
                        [
                            "が",
                            null
                        ],
                        [
                            "浮気",
                            "うわき"
                        ],
                        [
                            "を",
                            null
                        ],
                        [
                            "している",
                            null
                        ],
                        [
                            "ところ",
                            null
                        ],
                        [
                            "を",
                            null
                        ],
                        [
                            "見つかり",
                            "み"
                        ],
                        [
                            "でも",
                            null
                        ],
                        [
                            "しよう",
                            null
                        ],
                        [
                            "ものなら",
                            null
                        ],
                        [
                            "それ",
                            null
                        ],
                        [
                            "こそ",
                            null
                        ],
                        [
                            "コテンパン",
                            null
                        ],
                        [
                            "に",
                            null
                        ],
                        [
                            "やられて",
                            null
                        ],
                        [
                            "しまう",
                            null
                        ],
                        [
                            "よ",
                            null
                        ]
                    ],
                    "translation": "My wife used to be a pro-wrestler, so if she ever catches me two-timing her, I'd be beaten to a pulp."
                }
            ]
        },
        {
            "word": [
                [
                    "古",
                    "ふる"
                ]
            ],
            "common": false,
            "jlpt": null,
            "meanings": [
                {
                    "type": "Noun",
                    "meaning": "1. used item; secondhand item See also お古"
                },
                {
                    "type": "Noun, used as a prefix",
                    "meaning": "2. old; used; previous 森のはずれに古小屋が立っているのが見えた。We saw an old hut standing at the margin of the forest."
                },
                {
                    "type": "Place",
                    "meaning": "3. Furu "
                },
                {
                    "type": "Other forms",
                    "meaning": "故 【ふる】、旧 【ふる】"
                },
                {
                    "type": "Notes",
                    "meaning": "故: Rarely-used kanji form. 旧: Rarely-used kanji form."
                },
                {
                    "type": "Noun",
                    "meaning": "1. used item; secondhand item See also お古"
                },
                {
                    "type": "Noun, used as a prefix",
                    "meaning": "2. old; used; previous 森のはずれに古小屋が立っているのが見えた。We saw an old hut standing at the margin of the forest."
                },
                {
                    "type": "Place",
                    "meaning": "3. Furu "
                },
                {
                    "type": "Other forms",
                    "meaning": "故 【ふる】、旧 【ふる】"
                },
                {
                    "type": "Notes",
                    "meaning": "故: Rarely-used kanji form. 旧: Rarely-used kanji form."
                }
            ],
            "sentences": [
                {
                    "sentence": [
                        [
                            "森",
                            "もり"
                        ],
                        [
                            "の",
                            null
                        ],
                        [
                            "はずれ",
                            null
                        ],
                        [
                            "に",
                            null
                        ],
                        [
                            "古",
                            "ふる"
                        ],
                        [
                            "小屋",
                            "こや"
                        ],
                        [
                            "が",
                            null
                        ],
                        [
                            "立っている",
                            "た"
                        ],
                        [
                            "の",
                            null
                        ],
                        [
                            "が",
                            null
                        ],
                        [
                            "見えた",
                            "み"
                        ]
                    ],
                    "translation": "We saw an old hut standing at the margin of the forest."
                }
            ]
        },
        {
            "word": [
                [
                    "古",
                    "ふる"
                ],
                [
                    "い",
                    null
                ]
            ],
            "common": true,
            "jlpt": 5,
            "meanings": [
                {
                    "type": "I-adjective (keiyoushi)",
                    "meaning": "1. old; aged; ancient; antiquated; antique; timeworn of things, not people"
                },
                {
                    "type": "I-adjective (keiyoushi)",
                    "meaning": "2. long; since long ago; time-honored "
                },
                {
                    "type": "I-adjective (keiyoushi)",
                    "meaning": "3. of the distant past; long-ago "
                },
                {
                    "type": "I-adjective (keiyoushi)",
                    "meaning": "4. stale; threadbare; hackneyed; corny "
                },
                {
                    "type": "I-adjective (keiyoushi)",
                    "meaning": "5. old-fashioned; outmoded; out-of-date "
                },
                {
                    "type": "Other forms",
                    "meaning": "故い 【ふるい】、旧い 【ふるい】"
                },
                {
                    "type": "I-adjective (keiyoushi)",
                    "meaning": "1. old; aged; ancient; antiquated; antique; timeworn of things, not people"
                },
                {
                    "type": "I-adjective (keiyoushi)",
                    "meaning": "2. long; since long ago; time-honored "
                },
                {
                    "type": "I-adjective (keiyoushi)",
                    "meaning": "3. of the distant past; long-ago "
                },
                {
                    "type": "I-adjective (keiyoushi)",
                    "meaning": "4. stale; threadbare; hackneyed; corny "
                },
                {
                    "type": "I-adjective (keiyoushi)",
                    "meaning": "5. old-fashioned; outmoded; out-of-date "
                },
                {
                    "type": "Other forms",
                    "meaning": "故い 【ふるい】、旧い 【ふるい】"
                }
            ],
            "sentences": []
        },
        {
            "word": [
                [
                    "故",
                    "ふる"
                ],
                [
                    "郷",
                    "さと"
                ]
            ],
            "common": true,
            "jlpt": 3,
            "meanings": [
                {
                    "type": "Noun",
                    "meaning": "1. hometown; birthplace; native place; one's old home Usually written using kana alone, See also 故郷 こきょう"
                },
                {
                    "type": "Noun",
                    "meaning": "2. ruins; historic remains Archaic"
                },
                {
                    "type": "Other forms",
                    "meaning": "ふる里 【ふるさと】、古里 【ふるさと】、故里 【ふるさと】、旧里 【ふるさと】、旧里 【きゅうり】"
                },
                {
                    "type": "Notes",
                    "meaning": "故里: Rarely-used kanji form. 旧里: Rarely-used kanji form. 旧里: Rarely-used kanji form."
                },
                {
                    "type": "Noun",
                    "meaning": "1. hometown; birthplace; native place; one's old home Usually written using kana alone, See also 故郷 こきょう"
                },
                {
                    "type": "Noun",
                    "meaning": "2. ruins; historic remains Archaic"
                },
                {
                    "type": "Other forms",
                    "meaning": "ふる里 【ふるさと】、古里 【ふるさと】、故里 【ふるさと】、旧里 【ふるさと】、旧里 【きゅうり】"
                },
                {
                    "type": "Notes",
                    "meaning": "故里: Rarely-used kanji form. 旧里: Rarely-used kanji form. 旧里: Rarely-used kanji form."
                }
            ],
            "sentences": []
        },
        {
            "word": [
                [
                    "旧",
                    "きゅう"
                ],
                [
                    "式",
                    "しき"
                ]
            ],
            "common": true,
            "jlpt": null,
            "meanings": [
                {
                    "type": "Na-adjective (keiyodoshi), Noun which may take the genitive case particle 'no'",
                    "meaning": "1. old type; old style "
                },
                {
                    "type": "Na-adjective (keiyodoshi), Noun which may take the genitive case particle 'no'",
                    "meaning": "1. old type; old style "
                }
            ],
            "sentences": []
        },
        {
            "word": [
                [
                    "旧",
                    "きゅう"
                ],
                [
                    "友",
                    "ゆう"
                ]
            ],
            "common": false,
            "jlpt": null,
            "meanings": [
                {
                    "type": "Noun",
                    "meaning": "1. old friend; old pal "
                },
                {
                    "type": "Noun",
                    "meaning": "1. old friend; old pal "
                }
            ],
            "sentences": []
        },
        {
            "word": [
                [
                    "旧",
                    "きゅう"
                ],
                [
                    "型",
                    "がた"
                ]
            ],
            "common": false,
            "jlpt": null,
            "meanings": [
                {
                    "type": "Noun",
                    "meaning": "1. old style; old type "
                },
                {
                    "type": "Other forms",
                    "meaning": "旧型 【きゅうけい】"
                },
                {
                    "type": "Noun",
                    "meaning": "1. old style; old type "
                },
                {
                    "type": "Other forms",
                    "meaning": "旧型 【きゅうけい】"
                }
            ],
            "sentences": []
        },
        {
            "word": [
                [
                    "旧",
                    "きゅう"
                ],
                [
                    "暦",
                    "れき"
                ]
            ],
            "common": false,
            "jlpt": null,
            "meanings": [
                {
                    "type": "Noun",
                    "meaning": "1. Japan's old (lunisolar) calendar "
                },
                {
                    "type": "Noun",
                    "meaning": "1. Japan's old (lunisolar) calendar "
                }
            ],
            "sentences": []
        },
        {
            "word": [
                [
                    "旧",
                    "きゅう"
                ],
                [
                    "家",
                    "か"
                ]
            ],
            "common": false,
            "jlpt": null,
            "meanings": [
                {
                    "type": "Noun",
                    "meaning": "1. old family; old-established family "
                },
                {
                    "type": "Noun",
                    "meaning": "2. one's old home; one's childhood home "
                },
                {
                    "type": "Noun",
                    "meaning": "1. old family; old-established family "
                },
                {
                    "type": "Noun",
                    "meaning": "2. one's old home; one's childhood home "
                }
            ],
            "sentences": []
        },
        {
            "word": [
                [
                    "旧",
                    "きゅう"
                ],
                [
                    "知",
                    "ち"
                ]
            ],
            "common": false,
            "jlpt": 1,
            "meanings": [
                {
                    "type": "Noun",
                    "meaning": "1. old friend; old acquaintance "
                },
                {
                    "type": "Noun",
                    "meaning": "1. old friend; old acquaintance "
                }
            ],
            "sentences": [
                {
                    "sentence": [
                        [
                            "父親",
                            "ちちおや"
                        ],
                        [
                            "旧知",
                            "きゅうち"
                        ],
                        [
                            "間柄",
                            "あいだがら"
                        ]
                    ],
                    "translation": "As our fathers are old friends, my colleague and I have known each other since childhood."
                }
            ]
        },
        {
            "word": [
                [
                    "旧",
                    "きゅう"
                ],
                [
                    "体",
                    "たい"
                ],
                [
                    "制",
                    "せい"
                ]
            ],
            "common": false,
            "jlpt": null,
            "meanings": [
                {
                    "type": "Noun",
                    "meaning": "1. old regime "
                },
                {
                    "type": "Noun",
                    "meaning": "1. old regime "
                }
            ],
            "sentences": []
        },
        {
            "word": [
                [
                    "旧",
                    "きゅう"
                ],
                [
                    "弊",
                    "へい"
                ]
            ],
            "common": false,
            "jlpt": null,
            "meanings": [
                {
                    "type": "Noun",
                    "meaning": "1. old evils; long-standing abuses; old-fashioned ways; outdated notions "
                },
                {
                    "type": "Na-adjective (keiyodoshi)",
                    "meaning": "2. old-fashioned; outdated; outmoded; antiquated "
                },
                {
                    "type": "Other forms",
                    "meaning": "旧幣 【きゅうへい】"
                },
                {
                    "type": "Notes",
                    "meaning": "旧幣: Irregular kanji usage."
                },
                {
                    "type": "Noun",
                    "meaning": "1. old evils; long-standing abuses; old-fashioned ways; outdated notions "
                },
                {
                    "type": "Na-adjective (keiyodoshi)",
                    "meaning": "2. old-fashioned; outdated; outmoded; antiquated "
                },
                {
                    "type": "Other forms",
                    "meaning": "旧幣 【きゅうへい】"
                },
                {
                    "type": "Notes",
                    "meaning": "旧幣: Irregular kanji usage."
                }
            ],
            "sentences": []
        },
        {
            "word": [
                [
                    "旧",
                    "きゅう"
                ],
                [
                    "正",
                    "しょう"
                ],
                [
                    "月",
                    "がつ"
                ]
            ],
            "common": true,
            "jlpt": null,
            "meanings": [
                {
                    "type": "Noun",
                    "meaning": "1. lunar New Year (esp. the Chinese New Year) "
                },
                {
                    "type": "Wikipedia definition",
                    "meaning": "2. Chinese New Year Chinese New Year is the most important of the traditional... Read more"
                },
                {
                    "type": "Noun",
                    "meaning": "1. lunar New Year (esp. the Chinese New Year) "
                },
                {
                    "type": "Wikipedia definition",
                    "meaning": "2. Chinese New Year Chinese New Year is the most important of the traditional... Read more"
                }
            ],
            "sentences": []
        },
        {
            "word": [
                [
                    "旧",
                    "きゅう"
                ],
                [
                    "跡",
                    "せき"
                ]
            ],
            "common": false,
            "jlpt": null,
            "meanings": [
                {
                    "type": "Noun",
                    "meaning": "1. historic spot; historic site; place of historical interest; historic remains; ruins "
                },
                {
                    "type": "Other forms",
                    "meaning": "旧蹟 【きゅうせき】"
                },
                {
                    "type": "Noun",
                    "meaning": "1. historic spot; historic site; place of historical interest; historic remains; ruins "
                },
                {
                    "type": "Other forms",
                    "meaning": "旧蹟 【きゅうせき】"
                }
            ],
            "sentences": []
        },
        {
            "word": [
                [
                    "旧",
                    "きゅう"
                ],
                [
                    "石",
                    "せっきじだい"
                ],
                [
                    "器",
                    null
                ],
                [
                    "時",
                    null
                ],
                [
                    "代",
                    null
                ]
            ],
            "common": false,
            "jlpt": null,
            "meanings": [
                {
                    "type": "Noun",
                    "meaning": "1. Paleolithic; Palaeolithic; Old Stone Age "
                },
                {
                    "type": "Wikipedia definition",
                    "meaning": "2. Paleolithic The Paleolithic (or Palæolithic) Age, Era or Period, is a... Read more"
                },
                {
                    "type": "Noun",
                    "meaning": "1. Paleolithic; Palaeolithic; Old Stone Age "
                },
                {
                    "type": "Wikipedia definition",
                    "meaning": "2. Paleolithic The Paleolithic (or Palæolithic) Age, Era or Period, is a... Read more"
                }
            ],
            "sentences": []
        },
        {
            "word": [
                [
                    "旧",
                    "きゅう"
                ],
                [
                    "制",
                    "せい"
                ]
            ],
            "common": true,
            "jlpt": null,
            "meanings": [
                {
                    "type": "Noun",
                    "meaning": "1. old system; old order "
                },
                {
                    "type": "Noun",
                    "meaning": "1. old system; old order "
                }
            ],
            "sentences": []
        },
        {
            "word": [
                [
                    "旧",
                    "きゅう"
                ],
                [
                    "態",
                    "たい"
                ]
            ],
            "common": true,
            "jlpt": null,
            "meanings": [
                {
                    "type": "Noun",
                    "meaning": "1. old state of affairs "
                },
                {
                    "type": "Noun",
                    "meaning": "1. old state of affairs "
                }
            ],
            "sentences": [
                {
                    "sentence": [
                        [
                            "旧態依然",
                            "きゅうたいいぜん"
                        ]
                    ],
                    "translation": "Although this may seem old-fashioned in the Internet age, I check the meaning of foreign words by physically turning the pages of a dictionary. I feel that this old-fashioned way of learning a foreign language helps me remember the meaning of words more clearly."
                }
            ]
        },
        {
            "word": [
                [
                    "旧",
                    "きゅう"
                ],
                [
                    "派",
                    "は"
                ]
            ],
            "common": true,
            "jlpt": null,
            "meanings": [
                {
                    "type": "Noun, Noun which may take the genitive case particle 'no'",
                    "meaning": "1. old school; old style "
                }
            ],
            "sentences": []
        },
        {
            "word": [
                [
                    "旧",
                    "きゅう"
                ],
                [
                    "姓",
                    "せい"
                ]
            ],
            "common": true,
            "jlpt": null,
            "meanings": [
                {
                    "type": "Noun",
                    "meaning": "1. one's original family name; maiden name See also 現姓 げんせい"
                }
            ],
            "sentences": []
        },
        {
            "word": [
                "旧オソベツ川",
                "きゅうオソベツかわ"
            ],
            "common": false,
            "jlpt": null,
            "meanings": [
                {
                    "type": "Place",
                    "meaning": "1. Kyuuosobetsukawa "
                },
                {
                    "type": "Place",
                    "meaning": "1. Kyuusarobetsugawa "
                },
                {
                    "type": "Place",
                    "meaning": "1. former Soviet Union "
                }
            ],
            "sentences": []
        },
        {
            "word": [
                [
                    "復",
                    "ふっきゅう"
                ],
                [
                    "旧",
                    null
                ]
            ],
            "common": true,
            "jlpt": 1,
            "meanings": [
                {
                    "type": "Noun, Suru verb, Transitive verb, Intransitive verb, Noun which may take the genitive case particle 'no'",
                    "meaning": "1. restoration; restitution; rehabilitation "
                },
                {
                    "type": "Other forms",
                    "meaning": "復旧 【ふくきゅう】"
                }
            ],
            "sentences": []
        },
        {
            "word": [
                [
                    "旧",
                    "きゅう"
                ],
                [
                    "来",
                    "らい"
                ]
            ],
            "common": true,
            "jlpt": null,
            "meanings": [
                {
                    "type": "Noun which may take the genitive case particle 'no', Noun, Adverb (fukushi)",
                    "meaning": "1. traditional; from ancient times; formerly "
                }
            ],
            "sentences": []
        }
    ]
}